pomace/__init__.py
pomace/__main__.py
pomace/api.py
pomace/browser.py
pomace/cli.py
pomace/compat.py
pomace/config.py
pomace/enums.py
pomace/models.py
pomace/prompts.py
pomace/server.py
pomace/shared.py
pomace/tests/__init__.py
pomace/tests/cassettes/it_computes_values_based_on_the_html.yaml
pomace/tests/conftest.py
pomace/tests/test_browser.py
pomace/tests/test_enums.py
pomace/tests/test_models.py
pomace/tests/test_prompts.py
pomace/tests/test_types.py
pomace/types.py
pomace/utils.py
pomace-0.12.13.dist-info/LICENSE.md
pomace-0.12.13.dist-info/METADATA
pomace-0.12.13.dist-info/WHEEL
pomace-0.12.13.dist-info/entry_points.txt
pomace-0.12.13.dist-info/RECORD
