Metadata-Version: 2.3
Name: pomace
Version: 0.12.13
Summary: Dynamic page objects for browser automation.
License: MIT
Keywords: browser automation,page object model,selenium,splinter
Author: Jace Browning
Author-email: jacebrowning@gmail.com
Requires-Python: >=3.9,<4.0
Classifier: Development Status :: 4 - Beta
Classifier: Environment :: Console
Classifier: Intended Audience :: Developers
Classifier: License :: OSI Approved :: MIT License
Classifier: Natural Language :: English
Classifier: Operating System :: OS Independent
Classifier: Programming Language :: Python
Classifier: Programming Language :: Python :: 3
Classifier: Programming Language :: Python :: 3.9
Classifier: Programming Language :: Python :: 3.10
Classifier: Programming Language :: Python :: 3.11
Classifier: Programming Language :: Python :: 3.12
Classifier: Programming Language :: Python :: 3.13
Classifier: Topic :: Internet :: WWW/HTTP :: Browsers
Classifier: Topic :: Software Development :: Testing
Requires-Dist: beautifulsoup4 (>=4.8.2,<5.0.0)
Requires-Dist: bullet (>=2.2,<3.0)
Requires-Dist: cleo (>=2.0,<3.0)
Requires-Dist: datafiles (>=2.3.1,<3.0.0)
Requires-Dist: fake-useragent (>=1.3,<3.0)
Requires-Dist: faker (>=22)
Requires-Dist: flask-api (>=3.0,<4.0)
Requires-Dist: gitman (>=3.5.2,<4.0.0)
Requires-Dist: inflection (>=0.5.1,<0.6.0)
Requires-Dist: ipdb (>=0.13.9,<0.14.0)
Requires-Dist: ipython (>=8.4,<9.0)
Requires-Dist: minilog (>=2.3,<3.0)
Requires-Dist: nest-asyncio (>=1.5.5,<2.0.0)
Requires-Dist: parse (>=1.14,<2.0)
Requires-Dist: playwright (>=1.48,<2.0) ; platform_machine != "armv7l"
Requires-Dist: selenium (>=4.25,<5.0)
Requires-Dist: splinter (>=0.21,<0.22)
Requires-Dist: universal-startfile
Requires-Dist: us (>=3.1.1,<4.0.0)
Requires-Dist: webdriver_manager (>=4.0.2,<5.0.0)
Requires-Dist: werkzeug (<3)
Requires-Dist: zipcodes (>=1.2,<2.0)
Project-URL: Documentation, https://pomace.readthedocs.io
Project-URL: Homepage, https://pypi.org/project/pomace
Project-URL: Repository, https://github.com/jacebrowning/pomace
